agentlib/__init__.py
agentlib/core/__init__.py
agentlib/core/agent.py
agentlib/core/data_broker.py
agentlib/core/datamodels.py
agentlib/core/environment.py
agentlib/core/errors.py
agentlib/core/logging_.py
agentlib/core/model.py
agentlib/core/module.py
agentlib/models/__init__.py
agentlib/models/fmu_model.py
agentlib/models/scipy_model.py
agentlib/modules/__init__.py
agentlib/modules/communicator/__init__.py
agentlib/modules/communicator/clonemap.py
agentlib/modules/communicator/communicator.py
agentlib/modules/communicator/local.py
agentlib/modules/communicator/local_broadcast.py
agentlib/modules/communicator/local_multiprocessing.py
agentlib/modules/communicator/mqtt.py
agentlib/modules/controller/__init__.py
agentlib/modules/controller/bangbang.py
agentlib/modules/controller/controller.py
agentlib/modules/controller/pid.py
agentlib/modules/simulation/__init__.py
agentlib/modules/simulation/csv_data_source.py
agentlib/modules/simulation/simulator.py
agentlib/modules/utils/__init__.py
agentlib/modules/utils/agent_logger.py
agentlib/modules/utils/try_sensor.py
agentlib/utils/__init__.py
agentlib/utils/broker.py
agentlib/utils/fuzzy_matching.py
agentlib/utils/load_config.py
agentlib/utils/local_broadcast_broker.py
agentlib/utils/local_broker.py
agentlib/utils/multi_agent_system.py
agentlib/utils/multi_processing_broker.py
agentlib/utils/plugin_import.py
agentlib/utils/validators.py
agentlib/utils/plotting/__init__.py
agentlib/utils/plotting/simulator_dashboard.py
agentlib-0.8.9.dist-info/licenses/LICENSE
agentlib-0.8.9.dist-info/METADATA
agentlib-0.8.9.dist-info/WHEEL
agentlib-0.8.9.dist-info/top_level.txt
agentlib-0.8.9.dist-info/RECORD
