Metadata-Version: 2.4
Name: agentlib
Version: 0.8.9
Summary: Framework for development and execution of agents for control and simulation of energy systems.
Author-email: Associates of the AGENT project <AGENT.Projekt@eonerc.rwth-aachen.de>
License: BSD-3-Clause
Keywords: agents,modular,control,distributed,digital twin
Classifier: Programming Language :: Python :: 3.9
Classifier: Programming Language :: Python :: 3.10
Classifier: Programming Language :: Python :: 3.11
Classifier: Programming Language :: Python :: 3.12
Requires-Python: >=3.9
License-File: LICENSE
Requires-Dist: numpy>=1.17.4
Requires-Dist: pandas>=1.1.0
Requires-Dist: simpy>=4.0.1
Requires-Dist: pydantic>=2.0.0
Requires-Dist: attrs>=22.2.0
Provides-Extra: fmu
Requires-Dist: FMPy>=0.3.6; extra == "fmu"
Provides-Extra: scipy
Requires-Dist: scipy>=1.5.2; extra == "scipy"
Provides-Extra: plot
Requires-Dist: matplotlib; extra == "plot"
Provides-Extra: orjson
Requires-Dist: orjson>=3.9.15; extra == "orjson"
Provides-Extra: fuzz
Requires-Dist: rapidfuzz>=1.7.0; extra == "fuzz"
Provides-Extra: mqtt
Requires-Dist: paho-mqtt>=2.0.0; extra == "mqtt"
Provides-Extra: interactive
Requires-Dist: dash; extra == "interactive"
Requires-Dist: dash-bootstrap-components; extra == "interactive"
Requires-Dist: plotly; extra == "interactive"
Provides-Extra: deploy
Requires-Dist: agentlib[fmu,fuzz,mqtt,orjson,scipy]; extra == "deploy"
Provides-Extra: full
Requires-Dist: agentlib[fmu,fuzz,interactive,mqtt,orjson,plot,scipy]; extra == "full"
Dynamic: license-file
